aibou/__init__.py
aibou/__main__.py
aibou/data/__init__.py
aibou/data/monsters/__init__.py
aibou/data/monsters/angel.txt
aibou/data/monsters/anonymous.txt
aibou/data/monsters/babybee.txt
aibou/data/monsters/bat.txt
aibou/data/monsters/bowser.txt
aibou/data/monsters/centipede.txt
aibou/data/monsters/cobra.txt
aibou/data/monsters/hornet.txt
aibou/data/monsters/kitten.txt
aibou/data/monsters/rainbowcat.txt
aibou/data/monsters/saw.txt
aibou/data/monsters/smile1.txt
aibou/data/monsters/smile2.txt
aibou/data/monsters/smile3.txt
aibou/data/monsters/sphynx.txt
aibou/data/monsters/starter1.txt
aibou/data/monsters/starter2.txt
aibou/data/monsters/taz.txt
aibou/data/monsters/turtle.txt
aibou/data/monsters/wizard.txt
aibou/data/monsters/yoshi.txt
aibou/data/settings/__init__.py
aibou/data/settings/monsters.yaml
aibou/data/settings/moves.yaml
aibou/data/settings/settings.yaml
aibou/data/ui_art/__init__.py
aibou/data/ui_art/config.ascii
aibou/data/ui_art/info.ascii
aibou/data/ui_art/quickplay.ascii
aibou/data/ui_art/story.ascii
aibou/data/ui_art/title.ascii
aibou/docs/dev-notes.md
aibou/docs/how-to-play.md
aibou/docs/living-doc.md
aibou/screenshots/home.png
aibou/src/__init__.py
aibou/src/main.py
aibou/src/battle/ai.py
aibou/src/battle/battlemechanics.py
aibou/src/battle/getdata.py
aibou/src/battle/monster.py
aibou/src/battle/partnerturn.py
aibou/src/battle/qte.py
aibou/src/battle/runbattle.py
aibou/src/battle/settings.py
aibou/src/ui/__init__.py
aibou/src/ui/battlescreen.py
aibou/src/ui/color.py
aibou/src/ui/homescreen.py
aibou/src/ui/qtescreen.py
aibou/src/ui/screen.py
aibou-1.0.6.dist-info/LICENSE
aibou-1.0.6.dist-info/METADATA
aibou-1.0.6.dist-info/WHEEL
aibou-1.0.6.dist-info/top_level.txt
aibou-1.0.6.dist-info/RECORD
