Metadata-Version: 2.1
Name: aibou
Version: 1.0.6
Summary: Command line turn-based monster battle game
Author-email: Jacob Krol <jdkrol351@gmail.com>
License: MIT
Project-URL: Homepage, https://github.com/jakekrol/aibou
Classifier: Programming Language :: Python :: 3
Requires-Python: >=3.6
License-File: LICENSE
Requires-Dist: keyboard
Requires-Dist: rich
Requires-Dist: termcolor
Requires-Dist: PyYAML
